[
    {
        "type": "hi",
        "position": 1
    },
    {
        "type": "hi",
        "position": 2
    },
    {
        "type": "hi",
        "position": 6
    },
    {
        "type": "hi",
        "position": 7
    },
    {
        "type": "hi",
        "position": 11
    },
    {
        "type": "hi",
        "position": 12
    },
    {
        "type": "hi",
        "position": 16
    },
    {
        "type": "hi",
        "position": 17
    },
    {
        "type": "hi",
        "position": 21
    },
    {
        "type": "hi",
        "position": 22
    }
]